{"name": "啪啪",
"url": "https://www.javmost.cx",
"tihuan": "",
"ua": "Mozilla/5.0 (Windows NT 10.0; Win64; x64) AppleWebKit/537.36 (KHTML, like Gecko) Chrome/88.0.4324.150 Safari/537.36",
"直接播放": "1",
"列表显示": "0",
"横图显示": "1",
"shouye": "1",
"fenlei": "hh$/release/new/page/",
"houzhui": "/",
"shifouercijiequ": "0",
"jiequqian": "空",
"jiequhou": "空",
"jiequshuzuqian": "class=\"container2",
"jiequshuzuhou": "</div>",
"tupianqian": "data-src=\"",
"tupianhou": "\"",
"biaotiqian": "alt=\"",
"biaotihou": "\"",
"lianjieqian": "href=\"",
"lianjiehou": "\""
},